[
  {
    "region": "DIVE SITES MARATUA",
    "site": "Channel",
    "files": [
      {
        "url": "/assets/api/01_DIVE SITES MARATUA/01_Channel/Chevron barracuda_channel_maratua_09_08_26_armindo.jpg",
        "filename": "Chevron barracuda_channel_maratua_09_08_26_armindo.jpg",
        "type": "image",
        "metadata": {
          "species": "Chevron barracuda",
          "photographer": "armindo",
          "location": "Channel • DIVE SITES MARATUA"
        }
      },
      {
        "url": "/assets/api/01_DIVE SITES MARATUA/01_Channel/nembortha chrisata nudibranch_channel big country fish_maratua_04_03_24_yovi.jpeg",
        "filename": "nembortha chrisata nudibranch_channel big country fish_maratua_04_03_24_yovi.jpeg",
        "type": "image",
        "metadata": {
          "species": "nembortha chrisata nudibranch",
          "photographer": "yovi",
          "location": "Channel • DIVE SITES MARATUA"
        }
      }
    ]
  },
  {
    "region": "DIVE SITES MARATUA",
    "site": "Eel Garden",
    "files": [
      {
        "url": "/assets/api/01_DIVE SITES MARATUA/09_Eel Garden/Honeycomb moray_eel garden_maratua_09_03_26_armindo.jpeg",
        "filename": "Honeycomb moray_eel garden_maratua_09_03_26_armindo.jpeg",
        "type": "image",
        "metadata": {
          "species": "Honeycomb moray",
          "photographer": "armindo",
          "location": "Eel Garden • DIVE SITES MARATUA"
        }
      }
    ]
  },
  {
    "region": "DIVE SITES MARATUA",
    "site": "Turtle Traffic",
    "files": [
      {
        "url": "/assets/api/01_DIVE SITES MARATUA/17_Turtle Traffic/Halimeda ghost pipefish_turtle traffic_maratua_13_04_26_willi.JPG",
        "filename": "Halimeda ghost pipefish_turtle traffic_maratua_13_04_26_willi.JPG",
        "type": "image",
        "metadata": {
          "species": "Halimeda ghost pipefish",
          "photographer": "willi",
          "location": "Turtle Traffic • DIVE SITES MARATUA"
        }
      }
    ]
  },
  {
    "region": "DIVE SITES MARATUA",
    "site": "GNR Reef house",
    "files": [
      {
        "url": "/assets/api/01_DIVE SITES MARATUA/21_GNR Reef house/Caloria indica_sea slug_GNR Reef house_maaratua_04_03_26_yovi.jpeg",
        "filename": "Caloria indica_sea slug_GNR Reef house_maaratua_04_03_26_yovi.jpeg",
        "type": "image",
        "metadata": {
          "species": "Caloria indica",
          "photographer": "yovi",
          "location": "GNR Reef house • DIVE SITES MARATUA"
        }
      },
      {
        "url": "/assets/api/01_DIVE SITES MARATUA/21_GNR Reef house/Lembeh seadragon_ pipe horse_GNR Reef house_maratua_04_03_26_yovi.jpeg",
        "filename": "Lembeh seadragon_ pipe horse_GNR Reef house_maratua_04_03_26_yovi.jpeg",
        "type": "image",
        "metadata": {
          "species": "Lembeh seadragon",
          "photographer": "yovi",
          "location": "GNR Reef house • DIVE SITES MARATUA"
        }
      }
    ]
  },
  {
    "region": "DIVE SITES MARATUA",
    "site": "Green Nirvana Jetty",
    "files": [
      {
        "url": "/assets/api/01_DIVE SITES MARATUA/22_Green Nirvana Jetty/cumi-cumi bobtail_Sepiolida_green nirvana jetty_maratua_13_03_26_willi.JPG",
        "filename": "cumi-cumi bobtail_Sepiolida_green nirvana jetty_maratua_13_03_26_willi.JPG",
        "type": "image",
        "metadata": {
          "species": "cumi-cumi bobtail",
          "photographer": "willi",
          "location": "Green Nirvana Jetty • DIVE SITES MARATUA"
        }
      },
      {
        "url": "/assets/api/01_DIVE SITES MARATUA/22_Green Nirvana Jetty/Kepiting Harlequin _Lissocarcinus orbicularis_green nirvana jetty_maratua_13_03_26_willi.JPG",
        "filename": "Kepiting Harlequin _Lissocarcinus orbicularis_green nirvana jetty_maratua_13_03_26_willi.JPG",
        "type": "image",
        "metadata": {
          "species": "Kepiting Harlequin ",
          "photographer": "willi",
          "location": "Green Nirvana Jetty • DIVE SITES MARATUA"
        }
      }
    ]
  },
  {
    "region": "DIVE SITES MARATUA",
    "site": "Turtle point",
    "files": [
      {
        "url": "/assets/api/01_DIVE SITES MARATUA/23_Turtle point/Bumphead_tutrle point_maratua_13_03_26_willi.JPG",
        "filename": "Bumphead_tutrle point_maratua_13_03_26_willi.JPG",
        "type": "image",
        "metadata": {
          "species": "Bumphead",
          "photographer": "willi",
          "location": "Turtle point • DIVE SITES MARATUA"
        }
      },
      {
        "url": "/assets/api/01_DIVE SITES MARATUA/23_Turtle point/Pleurobranchus forskalii_ nudibranch_turtle point_maratua_13_02_26_willi.JPG",
        "filename": "Pleurobranchus forskalii_ nudibranch_turtle point_maratua_13_02_26_willi.JPG",
        "type": "image",
        "metadata": {
          "species": "Pleurobranchus forskalii",
          "photographer": "willi",
          "location": "Turtle point • DIVE SITES MARATUA"
        }
      }
    ]
  },
  {
    "region": "DIVE SITES MARATUA",
    "site": "Coral mountain bay",
    "files": [
      {
        "url": "/assets/api/01_DIVE SITES MARATUA/24_Coral mountain bay/Thresher shark_coral mountain bay_maratua_08_03_26_armindo.jpg",
        "filename": "Thresher shark_coral mountain bay_maratua_08_03_26_armindo.jpg",
        "type": "image",
        "metadata": {
          "species": "Thresher shark",
          "photographer": "armindo",
          "location": "Coral mountain bay • DIVE SITES MARATUA"
        }
      }
    ]
  },
  {
    "region": "DIVE SITES KAKABAN",
    "site": "The Wall",
    "files": [
      {
        "url": "/assets/api/02_DIVE SITES KAKABAN/03_The Wall/orangutan crab_the wall_kakaban_04_03_26_yovi.jpeg",
        "filename": "orangutan crab_the wall_kakaban_04_03_26_yovi.jpeg",
        "type": "image",
        "metadata": {
          "species": "orangutan crab",
          "photographer": "yovi",
          "location": "The Wall • DIVE SITES KAKABAN"
        }
      }
    ]
  },
  {
    "region": "DIVE SITES KAKABAN",
    "site": "Barracuda Point",
    "files": [
      {
        "url": "/assets/api/02_DIVE SITES KAKABAN/06_Barracuda Point/IMG_6913.PNG",
        "filename": "IMG_6913.PNG",
        "type": "image",
        "metadata": {
          "species": "IMG",
          "photographer": "6913",
          "location": "Barracuda Point • DIVE SITES KAKABAN"
        }
      },
      {
        "url": "/assets/api/02_DIVE SITES KAKABAN/06_Barracuda Point/Jack fish_ ikan kuwe_barracuda point_kakaban_09_03_26_armindo.jpg",
        "filename": "Jack fish_ ikan kuwe_barracuda point_kakaban_09_03_26_armindo.jpg",
        "type": "image",
        "metadata": {
          "species": "Jack fish",
          "photographer": "armindo",
          "location": "Barracuda Point • DIVE SITES KAKABAN"
        }
      }
    ]
  },
  {
    "region": "DIVE SITES KAKABAN",
    "site": "Tanjung Kelapa",
    "files": [
      {
        "url": "/assets/api/02_DIVE SITES KAKABAN/09_Tanjung Kelapa/Devilray_tanjung kelapa_kakaban_08_03_26_armindo.jpg",
        "filename": "Devilray_tanjung kelapa_kakaban_08_03_26_armindo.jpg",
        "type": "image",
        "metadata": {
          "species": "Devilray",
          "photographer": "armindo",
          "location": "Tanjung Kelapa • DIVE SITES KAKABAN"
        }
      },
      {
        "url": "/assets/api/02_DIVE SITES KAKABAN/09_Tanjung Kelapa/helgerda carlsoni_ nudibranch_tanjung kelapa_kakaban_04_03_26_yovi.jpeg",
        "filename": "helgerda carlsoni_ nudibranch_tanjung kelapa_kakaban_04_03_26_yovi.jpeg",
        "type": "image",
        "metadata": {
          "species": "helgerda carlsoni",
          "photographer": "yovi",
          "location": "Tanjung Kelapa • DIVE SITES KAKABAN"
        }
      }
    ]
  },
  {
    "region": "DIVE SITES KAKABAN",
    "site": "Kelapa Dua",
    "files": [
      {
        "url": "/assets/api/02_DIVE SITES KAKABAN/10_Kelapa Dua/Acropoda Yongei_kelapa dua_kakaban_04_03_25_azman.jpeg",
        "filename": "Acropoda Yongei_kelapa dua_kakaban_04_03_25_azman.jpeg",
        "type": "image",
        "metadata": {
          "species": "Acropoda Yongei",
          "photographer": "azman",
          "location": "Kelapa Dua • DIVE SITES KAKABAN"
        }
      },
      {
        "url": "/assets/api/02_DIVE SITES KAKABAN/10_Kelapa Dua/antennarius commerson_ giant frogfish_kelapa dua_kakaban_04_03_26_yovi.jpeg",
        "filename": "antennarius commerson_ giant frogfish_kelapa dua_kakaban_04_03_26_yovi.jpeg",
        "type": "image",
        "metadata": {
          "species": "antennarius commerson",
          "photographer": "yovi",
          "location": "Kelapa Dua • DIVE SITES KAKABAN"
        }
      },
      {
        "url": "/assets/api/02_DIVE SITES KAKABAN/10_Kelapa Dua/Blue encrushting coral_ kelapa dua_kakaban_04_03_25_azman.jpeg",
        "filename": "Blue encrushting coral_ kelapa dua_kakaban_04_03_25_azman.jpeg",
        "type": "image",
        "metadata": {
          "species": "Blue encrushting coral",
          "photographer": "azman",
          "location": "Kelapa Dua • DIVE SITES KAKABAN"
        }
      },
      {
        "url": "/assets/api/02_DIVE SITES KAKABAN/10_Kelapa Dua/blueYellow Finger coral_kelapa dua_kakaban_04_03_25_azman.jpeg",
        "filename": "blueYellow Finger coral_kelapa dua_kakaban_04_03_25_azman.jpeg",
        "type": "image",
        "metadata": {
          "species": "blueYellow Finger coral",
          "photographer": "azman",
          "location": "Kelapa Dua • DIVE SITES KAKABAN"
        }
      },
      {
        "url": "/assets/api/02_DIVE SITES KAKABAN/10_Kelapa Dua/Bubble coral_kelapa dua_kakaban_04_03_25_azman.jpeg",
        "filename": "Bubble coral_kelapa dua_kakaban_04_03_25_azman.jpeg",
        "type": "image",
        "metadata": {
          "species": "Bubble coral",
          "photographer": "azman",
          "location": "Kelapa Dua • DIVE SITES KAKABAN"
        }
      },
      {
        "url": "/assets/api/02_DIVE SITES KAKABAN/10_Kelapa Dua/Cactus coral_kelapa dua_kakaban_04_03_25_azman.jpeg",
        "filename": "Cactus coral_kelapa dua_kakaban_04_03_25_azman.jpeg",
        "type": "image",
        "metadata": {
          "species": "Cactus coral",
          "photographer": "azman",
          "location": "Kelapa Dua • DIVE SITES KAKABAN"
        }
      },
      {
        "url": "/assets/api/02_DIVE SITES KAKABAN/10_Kelapa Dua/Elkhorn coral_kelapa dua_kakaban_04_03_25_azman.jpeg",
        "filename": "Elkhorn coral_kelapa dua_kakaban_04_03_25_azman.jpeg",
        "type": "image",
        "metadata": {
          "species": "Elkhorn coral",
          "photographer": "azman",
          "location": "Kelapa Dua • DIVE SITES KAKABAN"
        }
      },
      {
        "url": "/assets/api/02_DIVE SITES KAKABAN/10_Kelapa Dua/Honeycomb coral_kelapa dua_kakaban_04_03_25_azman.jpeg",
        "filename": "Honeycomb coral_kelapa dua_kakaban_04_03_25_azman.jpeg",
        "type": "image",
        "metadata": {
          "species": "Honeycomb coral",
          "photographer": "azman",
          "location": "Kelapa Dua • DIVE SITES KAKABAN"
        }
      },
      {
        "url": "/assets/api/02_DIVE SITES KAKABAN/10_Kelapa Dua/Phyllodesmium brigreum _ nudibranch_Kelapadua_kakaban_04_03_26_yovi.jpeg",
        "filename": "Phyllodesmium brigreum _ nudibranch_Kelapadua_kakaban_04_03_26_yovi.jpeg",
        "type": "image",
        "metadata": {
          "species": "Phyllodesmium brigreum ",
          "photographer": "yovi",
          "location": "Kelapa Dua • DIVE SITES KAKABAN"
        }
      },
      {
        "url": "/assets/api/02_DIVE SITES KAKABAN/10_Kelapa Dua/staghorn coral_kelapa dua_kakaban_04_03_25_azman.jpeg",
        "filename": "staghorn coral_kelapa dua_kakaban_04_03_25_azman.jpeg",
        "type": "image",
        "metadata": {
          "species": "staghorn coral",
          "photographer": "azman",
          "location": "Kelapa Dua • DIVE SITES KAKABAN"
        }
      },
      {
        "url": "/assets/api/02_DIVE SITES KAKABAN/10_Kelapa Dua/Thresher shark_kelapa dua_kakaban_08_03_26_armindo.jpg",
        "filename": "Thresher shark_kelapa dua_kakaban_08_03_26_armindo.jpg",
        "type": "image",
        "metadata": {
          "species": "Thresher shark",
          "photographer": "armindo",
          "location": "Kelapa Dua • DIVE SITES KAKABAN"
        }
      }
    ]
  },
  {
    "region": "DIVE SITES KAKABAN",
    "site": "Kakaban Jetty",
    "files": [
      {
        "url": "/assets/api/02_DIVE SITES KAKABAN/13_Kakaban Jetty/Spons laut_ Xestospongia muta_kakaban jetty_kakaban_26_03_26_willi.JPG",
        "filename": "Spons laut_ Xestospongia muta_kakaban jetty_kakaban_26_03_26_willi.JPG",
        "type": "image",
        "metadata": {
          "species": "Spons laut",
          "photographer": "willi",
          "location": "Kakaban Jetty • DIVE SITES KAKABAN"
        }
      }
    ]
  },
  {
    "region": "DIVE SITES KAKABAN",
    "site": "sisip kakaban",
    "files": [
      {
        "url": "/assets/api/02_DIVE SITES KAKABAN/14_sisip kakaban/Melichthys niger_pogot hitam_sisip kakaban_kakaban_09_03_26_armindo.jpg",
        "filename": "Melichthys niger_pogot hitam_sisip kakaban_kakaban_09_03_26_armindo.jpg",
        "type": "image",
        "metadata": {
          "species": "Melichthys niger",
          "photographer": "armindo",
          "location": "sisip kakaban • DIVE SITES KAKABAN"
        }
      }
    ]
  },
  {
    "region": "DIVE SITES DERAWAN",
    "site": "Macro Mania",
    "files": [
      {
        "url": "/assets/api/03_DIVE SITES DERAWAN/08_Macro Mania/Nudibranch_macro mania_derawan_13_03_26_willi.JPG",
        "filename": "Nudibranch_macro mania_derawan_13_03_26_willi.JPG",
        "type": "image",
        "metadata": {
          "species": "Nudibranch",
          "photographer": "willi",
          "location": "Macro Mania • DIVE SITES DERAWAN"
        }
      }
    ]
  },
  {
    "region": "DIVE SITES DERAWAN",
    "site": "Darma Point",
    "files": [
      {
        "url": "/assets/api/03_DIVE SITES DERAWAN/11_Darma Point/Thecacera sp_nudibranch_Darma point_Derawan_04_03_26_yovi.jpeg",
        "filename": "Thecacera sp_nudibranch_Darma point_Derawan_04_03_26_yovi.jpeg",
        "type": "image",
        "metadata": {
          "species": "Thecacera sp",
          "photographer": "yovi",
          "location": "Darma Point • DIVE SITES DERAWAN"
        }
      }
    ]
  },
  {
    "region": "DIVE SITES DERAWAN",
    "site": "Pulau Panjang",
    "files": [
      {
        "url": "/assets/api/03_DIVE SITES DERAWAN/12_Pulau Panjang/Ghost Pipefish_Pulau panjang_derawan_13_03_26_willi.JPG",
        "filename": "Ghost Pipefish_Pulau panjang_derawan_13_03_26_willi.JPG",
        "type": "image",
        "metadata": {
          "species": "Ghost Pipefish",
          "photographer": "willi",
          "location": "Pulau Panjang • DIVE SITES DERAWAN"
        }
      }
    ]
  }
]